REST/__init__.py
REST/keywords.py
REST/schema_keywords.py
REST/version.py
restinstance-1.6.2.dist-info/licenses/LICENSE.txt
restinstance-1.6.2.dist-info/METADATA
restinstance-1.6.2.dist-info/WHEEL
restinstance-1.6.2.dist-info/top_level.txt
restinstance-1.6.2.dist-info/RECORD
