Metadata-Version: 2.4
Name: RESTinstance
Version: 1.6.2
Summary: Robot Framework library for RESTful JSON APIs
Author-email: Anssi Syrjäsalo <opensource@syrjasalo.com>
License: LGPLv3
Project-URL: Homepage, https://pypi.org/project/RESTinstance
Project-URL: Documentation, https://asyrjasalo.github.io/RESTinstance
Project-URL: Repository, https://github.com/asyrjasalo/RESTinstance
Keywords: robotframework,library,http,json,api
Classifier: Development Status :: 5 - Production/Stable
Classifier: License :: OSI Approved :: GNU Lesser General Public License v3 (LGPLv3)
Classifier: Operating System :: OS Independent
Classifier: Programming Language :: Python :: 3.9
Classifier: Programming Language :: Python :: 3.10
Classifier: Programming Language :: Python :: 3.11
Classifier: Programming Language :: Python :: 3.12
Classifier: Programming Language :: Python :: 3.13
Classifier: Framework :: Robot Framework
Classifier: Framework :: Robot Framework :: Library
Classifier: Topic :: Software Development :: Libraries :: Python Modules
Classifier: Topic :: Software Development :: Testing
Requires-Python: >=3.9
License-File: LICENSE.txt
Requires-Dist: docutils
Requires-Dist: flex
Requires-Dist: GenSON
Requires-Dist: jsonpath-ng
Requires-Dist: jsonschema
Requires-Dist: openapi-core
Requires-Dist: pygments
Requires-Dist: pytz
Requires-Dist: requests
Requires-Dist: robotframework
Requires-Dist: tzlocal
Requires-Dist: setuptools<80
Dynamic: license-file
